{
  "project_info": {
    "project_number": "50778628971",
    "project_id": "my-cool-project-1202202",
    "storage_bucket": "my-cool-project-1202202.firebasestorage.app"
  },
  "client": [
    {
      "client_info": {
        "mobilesdk_app_id": "1:50778628971:android:1975e0d13c7828acc8a22e",
        "android_client_info": {
          "package_name": "com.example.myapp"
        }
      },
      "oauth_client": [],
      "api_key": [
        {
          "current_key": "AIzaSyAD3PqRgTrtcC-iYAWonMfakFNRvP6NHZU"
        }
      ],
      "services": {
        "appinvite_service": {
          "other_platform_oauth_client": []
        }
      }
    }
  ],
  "configuration_version": "1"
}